front_data/__init__.py
front_data/admin.py
front_data/apps.py
front_data/models.py
front_data/serializers.py
front_data/urls.py
front_data/views.py
front_data/migrations/0001_initial.py
front_data/migrations/0002_configuration.py
front_data/migrations/__init__.py
front_data/templates/site_data/editorJson.html
django_front_data-1.2.0.dist-info/LICENSE
django_front_data-1.2.0.dist-info/METADATA
django_front_data-1.2.0.dist-info/WHEEL
django_front_data-1.2.0.dist-info/top_level.txt
django_front_data-1.2.0.dist-info/RECORD
