Metadata-Version: 2.1
Name: django-front-data
Version: 1.2.0
Summary: Create django front-end data apps
Home-page: https://github.com/mahbd/django-front-data
Author: Mahmudul Alam
Author-email: mahmudula2000@gmail.com
License: MIT
Platform: UNKNOWN
Classifier: License :: OSI Approved :: MIT License
Classifier: Operating System :: OS Independent
Classifier: Environment :: Web Environment
Classifier: Programming Language :: Python :: 3
Classifier: Programming Language :: Python :: 3.10
Classifier: Framework :: Django
Classifier: Framework :: Django :: 3.2
License-File: LICENSE
Requires-Dist: django (>=3.2.0)
